LICENSE
MANIFEST.in
README.md
setup.py
banter/__init__.py
banter/banter.py
banter/config.py
banter/config_ui.py
banter/crucible.py
banter/dict2xml.py
banter/patch.py
banter/utils.py
banter.egg-info/PKG-INFO
banter.egg-info/SOURCES.txt
banter.egg-info/dependency_links.txt
banter.egg-info/entry_points.txt
banter.egg-info/requires.txt
banter.egg-info/top_level.txt
test/test_banter.py
test/test_config.py
test/test_crucible.py
test/test_dict2xml.py
test/test_patch.py
test/test_utils.py