Metadata-Version: 1.1
Name: banter
Version: 0.2.1
Summary: Create crucible code reviews from the command line
Home-page: http://github.com/markdrago/banter
Author: Mark Drago
Author-email: markdrago@gmail.com
License: MIT
Download-URL: http://pypi.python.org/pypi/banter
Platform: UNKNOWN
Classifier: Programming Language :: Python :: 2
Classifier: Programming Language :: Python :: 3
Classifier: License :: OSI Approved :: MIT License
Classifier: Operating System :: POSIX
Classifier: Development Status :: 4 - Beta
Classifier: Intended Audience :: Developers
Classifier: Topic :: Software Development :: Quality Assurance
Classifier: Topic :: Software Development :: Testing
Classifier: Topic :: Utilities
